switch_guides/SwitchGuideTask.py
switch_guides/__init__.py
switch_guides/exceptions.py
switch_guides/extensions/__init__.py
switch_guides/extensions/cache/__init__.py
switch_guides/extensions/cache/cache.py
switch_guides/extensions/component/__init__.py
switch_guides/extensions/component/form_data.py
switch_guides/extensions/component/forms.py
switch_guides/models/__init__.py
switch_guides/models/api.py
switch_guides/models/enums.py
switch_guides/models/guide.py
switch_guides/models/literals.py
switch_guides/models/step.py
switch_guides/pipeline/__init__.py
switch_guides/pipeline/automation.py
switch_guides/tasks/GuideDefinitionTask.py
switch_guides/tasks/GuideRetrySupportTask.py
switch_guides/tasks/GuideStepDefinitionBackgroundTask.py
switch_guides/tasks/GuideStepDefinitionTask.py
switch_guides/tasks/__init__.py
switch_guides/utils/__init__.py
switch_guides/utils/utils.py
switch_guides-0.2.7.dist-info/AUTHORS.rst
switch_guides-0.2.7.dist-info/LICENCE
switch_guides-0.2.7.dist-info/METADATA
switch_guides-0.2.7.dist-info/WHEEL
switch_guides-0.2.7.dist-info/top_level.txt
switch_guides-0.2.7.dist-info/RECORD
