Metadata-Version: 2.1
Name: switch-guides
Version: 0.2.7
Summary: A package for building Platform Guides in Switch Automation Platform.
Home-page: UNKNOWN
Author: Switch Automation Pty Ltd.
License: MIT License
Platform: UNKNOWN
Classifier: Development Status :: 2 - Pre-Alpha
Classifier: License :: OSI Approved :: MIT License
Classifier: Intended Audience :: Other Audience
Classifier: Programming Language :: Python :: 3
Classifier: Programming Language :: Python :: 3.8
Classifier: Programming Language :: Python :: 3.9
Classifier: Natural Language :: English
Requires-Python: >=3.8.0
License-File: LICENCE
License-File: AUTHORS.rst
Requires-Dist: switch-api
Requires-Dist: pydantic (<2.0.0,>=1.0.0)
